CryDBkit/__init__.py
CryDBkit/website.py
CryDBkit-0.1.1.dist-info/METADATA
CryDBkit-0.1.1.dist-info/WHEEL
CryDBkit-0.1.1.dist-info/top_level.txt
CryDBkit-0.1.1.dist-info/RECORD
